<adminmenu>
    <menuitems>
        <menuitem>
            <mask>EditUploads</mask>
            <includes>
                <includeitem>view</includeitem>
            </includes>
            <target>view</target>
            <title>View the uploaded files on this site</title>
            <label>View Files</label>
        </menuitem>
        <menuitem>
            <mask>AddUploads</mask>
            <includes>
                <includeitem>get_files</includeitem>
            </includes>
            <target>get_files</target>
            <title>Upload a new file</title>
            <label>Add File</label>
        </menuitem>
        <menuitem>
            <mask>EditUploads</mask>
            <includes>
                <includeitem>assoc</includeitem>
            </includes>
            <target>assoc</target>
            <title>View the known file associations</title>
            <label>View Assciations</label>
        </menuitem>
        <menuitem>
            <mask>AdminUploads</mask>
            <includes>
                <includeitem>modifyconfig</includeitem>
            </includes>
            <target>modifyconfig</target>
            <title>Modify configuration settings of this module</title>
            <label>Modify Configuration</label>
        </menuitem>
        <menuitem>
            <includes>
                <includeitem>main</includeitem>
                <includeitem>overview</includeitem>
            </includes>
            <target>main</target>
            <label>Overview</label>
        </menuitem>
  </menuitems>
</adminmenu>
