<object name="ice_taxclasses">
  <objectid>31</objectid>
  <label>Tax Classes</label>
  <moduleid>182</moduleid>
  <itemtype>6</itemtype>
  <urlparam>itemid</urlparam>
  <maxid>0</maxid>
  <config></config>
  <isalias>0</isalias>
  <properties>
    <property name="class_id">
      <id>188</id>
      <label>Class Id</label>
      <type>itemid</type>
      <default></default>
      <source>dynamic_data</source>
      <status>34</status>
      <order>1</order>
      <validation>int (11)</validation>
    </property>
    <property name="class_title">
      <id>189</id>
      <label>Class Title</label>
      <type>textbox</type>
      <default></default>
      <source>dynamic_data</source>
      <status>33</status>
      <order>2</order>
      <validation>0:32</validation>
    </property>
    <property name="class_description">
      <id>190</id>
      <label>Class Description</label>
      <type>textbox</type>
      <default></default>
      <source>dynamic_data</source>
      <status>33</status>
      <order>3</order>
      <validation>0:255</validation>
    </property>
    <property name="modified">
      <id>191</id>
      <label>Modified</label>
      <type>calendar</type>
      <default></default>
      <source>dynamic_data</source>
      <status>34</status>
      <order>4</order>
      <validation>datetime</validation>
    </property>
    <property name="added">
      <id>192</id>
      <label>Added</label>
      <type>calendar</type>
      <default></default>
      <source>dynamic_data</source>
      <status>34</status>
      <order>5</order>
      <validation>datetime</validation>
    </property>
  </properties>
</object>
