<object name="ice_taxzonemapping">
  <objectid>79</objectid>
  <label>Tax zone mapping</label>
  <moduleid>182</moduleid>
  <itemtype>10</itemtype>
  <urlparam>itemid</urlparam>
  <maxid>0</maxid>
  <config></config>
  <isalias>0</isalias>
  <properties>
    <property name="id">
      <id>504</id>
      <label>Id</label>
      <type>itemid</type>
      <default></default>
      <source>dynamic_data</source>
      <status>33</status>
      <order>1</order>
      <validation>int (11)</validation>
    </property>
    <property name="country_id">
      <id>505</id>
      <label>Country Id</label>
      <type>integerbox</type>
      <default></default>
      <source>dynamic_data</source>
      <status>33</status>
      <order>2</order>
      <validation>int (11)</validation>
    </property>
    <property name="zone_id">
      <id>506</id>
      <label>Zone ID</label>
      <type>integerbox</type>
      <default></default>
      <source>dynamic_data</source>
      <status>33</status>
      <order>3</order>
      <validation>int (11)</validation>
    </property>
    <property name="geozone_id">
      <id>507</id>
      <label>Geozone ID</label>
      <type>integerbox</type>
      <default></default>
      <source>dynamic_data</source>
      <status>33</status>
      <order>4</order>
      <validation>int (11)</validation>
    </property>
    <property name="modified">
      <id>508</id>
      <label>Modified</label>
      <type>calendar</type>
      <default></default>
      <source>dynamic_data</source>
      <status>33</status>
      <order>5</order>
      <validation>datetime</validation>
    </property>
    <property name="added">
      <id>509</id>
      <label>Added</label>
      <type>calendar</type>
      <default></default>
      <source>dynamic_data</source>
      <status>33</status>
      <order>6</order>
      <validation>datetime</validation>
    </property>
  </properties>
</object>
